xh_cpu_usage_simulator/LinearRegressionPrediction.py
xh_cpu_usage_simulator/MovingAvg.py
xh_cpu_usage_simulator/PsMonitor.py
xh_cpu_usage_simulator/TaskWorker.py
xh_cpu_usage_simulator/TestMovingAvg.py
xh_cpu_usage_simulator/__main__.py
xh_cpu_usage_simulator-0.1.3.dist-info/LICENSE.txt
xh_cpu_usage_simulator-0.1.3.dist-info/METADATA
xh_cpu_usage_simulator-0.1.3.dist-info/WHEEL
xh_cpu_usage_simulator-0.1.3.dist-info/top_level.txt
xh_cpu_usage_simulator-0.1.3.dist-info/RECORD
