Metadata-Version: 2.1
Name: xh-cpu-usage-simulator
Version: 0.1.3
Summary: Tools simulating the cpu usage
Author-email: xethhung <pypi@xethh.dev>
Project-URL: Homepage, https://github.com/xh-dev/xh-dict-utils
Project-URL: Bug Tracker, https://github.com/xh-dev/xh-dict-utils/issues
Classifier: Programming Language :: Python :: 3
Classifier: License :: OSI Approved :: MIT License
Classifier: Operating System :: OS Independent
Requires-Python: >=3.6
License-File: LICENSE.txt
Requires-Dist: psutil (==5.9.5)
Requires-Dist: scikit-learn (==1.2.2)
Requires-Dist: numpy (==1.24.2)
